{
  "core-registry-cadt": {
    "name": "cadt",
    "version": "1.7.1",
    "repo": "https://github.com/Chia-Network/Core-Registry-CADT/",
    "filename_format": "${APP}-${OS}-${ARCH}-${VERSION}.zip",
    "executable_format": "${APP}",
    "folder": "${APP}-${OS}-${ARCH}"
  },
  "climate-explorer-chia": {
    "name": "climate_explorer",
    "version": "1.0.37",
    "repo": "https://github.com/Chia-Network/climate-token-driver/",
    "filename_format": "${APP}_${OS}_${VERSION}_${ARCH}.zip",
    "executable_format": "${APP}_${VERSION}_${ARCH}"
  },
  "climate-tokenization-engine": {
    "name": "climate_token_engine",
    "version": "1.3.16",
    "repo": "https://github.com/Chia-Network/Climate-Tokenization-Engine/",
    "filename_format": "${APP}-${OS}-${ARCH}-${VERSION}.zip",
    "executable_format": "${APP}",
    "folder": "${APP}-${OS}-${ARCH}"
  },
  "climate-tokenization-chia": {
    "name": "climate_token_driver",
    "version": "1.0.37",
    "repo": "https://github.com/Chia-Network/climate-token-driver/",
    "filename_format": "${APP}_${OS}_${VERSION}_${ARCH}.zip",
    "executable_format": "${APP}_${VERSION}_${ARCH}"
  }
}
